etc/__init__.py
etc/choices.py
etc/forms.py
etc/importing.py
etc/models.py
etc/sites.py
etc/toolbox.py
etc/admin/__init__.py
etc/admin/admins.py
etc/admin/models.py
etc/templatetags/__init__.py
etc/templatetags/etc_misc.py
etc/templatetags/gravatar.py
etc/templatetags/model_field.py
etc/templatetags/model_meta.py
etc/tests/__init__.py
etc/tests/conftest.py
etc/tests/test_admin.py
etc/tests/test_basic.py
etc/tests/testapp/__init__.py
etc/tests/testapp/admin.py
etc/tests/testapp/models.py
etc/tests/testapp/urls.py
etc/tests/testapp/views.py
django_etc-1.3.1.dist-info/AUTHORS
django_etc-1.3.1.dist-info/LICENSE
django_etc-1.3.1.dist-info/METADATA
django_etc-1.3.1.dist-info/WHEEL
django_etc-1.3.1.dist-info/top_level.txt
django_etc-1.3.1.dist-info/RECORD
